twth_payslip_parser/__init__.py
twth_payslip_parser/decrypter.py
twth_payslip_parser/parser.py
twth_payslip_parser-0.1.1.dist-info/METADATA
twth_payslip_parser-0.1.1.dist-info/WHEEL
twth_payslip_parser-0.1.1.dist-info/entry_points.txt
twth_payslip_parser-0.1.1.dist-info/RECORD
