Metadata-Version: 2.1
Name: twth-payslip-parser
Version: 0.1.1
Summary: 
Author: leprechaun
Author-email: leprechaun@gmail.com
Requires-Python: >=3.11,<4.0
Classifier: Programming Language :: Python :: 3
Classifier: Programming Language :: Python :: 3.11
Classifier: Programming Language :: Python :: 3.12
Requires-Dist: pdfquery (>=0.4.3,<0.5.0)
Requires-Dist: pypdf2 (>=3.0.1,<4.0.0)
